analysis/__init__.py
analysis/anova.py
analysis/factor_effect.py
analysis/plot.py
common/__init__.py
common/util/__init__.py
doe/__init__.py
doe/orthogonal_array.py
doelab-0.1.1.dist-info/METADATA
doelab-0.1.1.dist-info/WHEEL
doelab-0.1.1.dist-info/RECORD
